roukf/__init__.py
roukf-0.1.0.dist-info/METADATA
roukf-0.1.0.dist-info/WHEEL
roukf-0.1.0.dist-info/top_level.txt
roukf-0.1.0.dist-info/RECORD
