Metadata-Version: 2.1
Name: roukf
Version: 0.1.0
Summary: ROUKF - Kalman filter for parameter estimation
Author: Gonzalo Maso Talou
Author-email: g.masotalou@auckland.ac.nz
Requires-Dist: numpy
